{
  "root": {
    "name": "",
    "description": "",
    "sections": {
      "part1": {
        "rules": {
          "deck_player": {
            "use_deck": "",
            "allow_user_decks": "1",
            "additional_decks": {},
            "validator": {}
          },
          "deck_ai": {
            "use_deck": "",
            "allow_user_decks": "1",
            "additional_decks": {
              "sample_deck_1": {
                "name": "A",
                "description": "",
                "tags": "",
                "code": ""
              }
            },
            "validator": {}
          },
          "set1": "1",
          "store_enabled": "1",

          "initial_heroes": "3",
          "initial_heroes_ai": "3",

          "tower1_health": "40",
          "tower2_health": "40",
          "tower3_health": "40",
          "tower1_health_ai": "40",
          "tower2_health_ai": "40",
          "tower3_health_ai": "40",

          "ancient1_health": "80",
          "ancient2_health": "80",
          "ancient3_health": "80",
          "ancient1_health_ai": "80",
          "ancient2_health_ai": "80",
          "ancient3_health_ai": "80",

          "initial_mana": "5",
          "initial_mana_ai": "5",

          "creeps_first_turn": "5",
          "creeps_first_turn_ai": "10",
          "creeps_per_turn": "1",
          "creeps_per_turn_ai": "10",

          "cards_first_turn": "5",
          "cards_first_turn_ai": "5",
          "cards_per_turn": "2",
          "cards_per_turn_ai": "2",
          "free_cards_per_turn": "",
          "free_cards_per_turn_ai": "",

          "gold_per_turn_ai": "3",

          "mana_boost_per_turn_ai": "0",

          "creep_list": "1006",
          "creep_list_ai": "1006",

          "deploy_heroes_enabled": "1",

          "gold_victory": "0",

          "ai_pass_chance_multiplier": "50",
          "creeps_lanes_player_1each": "0",

          "creeps_lanes_random": "1",

          "heroes_initial_lane_random": "1",

          "hero1_player": "0",
          "hero2_player": "0",
          "hero3_player": "0",
          "hero1_ai": "0",
          "hero2_ai": "0",
          "hero3_ai": "0",

          "only_flop_across_from_heroes": "0",
          "no_shotclock": "0",
          "shotclock_base_time": "45",
          "force_combat_manager_rand_to_zero": "0",
          "ai_action_choice_non_random": "0",
          "defense_shield_force": ""
        },
        "deck_order_player": {},
        "deck_order_ai": {},
        "sequences": {
          "start": {},
          "end": {}
        }
      }
    }
  }
}